{
    "name": "cypher",
    "title": "Cypher",
    "description": "A fork of SolarBear's Numenera system for use with non-specific Cypher System games.",
    "version": "0.6.3",
    "author": "cmark89",
    "scripts": ["lib/dragula/dragula.min.js"],
    "esmodules": ["numenera.js"],
    "styles": ["numenera.css", "lib/dragula/dragula.min.css"],
    "packs": [],
    "languages": ["en"],
    "compatibleCoreVersion": "0.5.7",
    "minimumCoreVersion" : "0.5.7",
    "url": "https://github.com/cmark89/Cypher-FoundryVTT",
    "manifest": "https://raw.githubusercontent.com/cmark89/Cypher-FoundryVTT/master/system.json",
    "download": "https://github.com/SolarBear/Numenera-FoundryVTT/releases/download/0.6.3/numenera-foundryvtt-0.6.3.zip"
}
